conjur/__init__.py
conjur/__main__.py
conjur/api.py
conjur/cli.py
conjur/client.py
conjur/config.py
conjur/endpoints.py
conjur/http.py
conjur/version.py
conjur_client-0.1.1.data/scripts/conjur-cli
pkg_bin/__init__.py
test/__init__.py
test/test_api.py
test/test_cli.py
test/test_cli_integration.py
test/test_client.py
test/test_config.py
test/test_endpoints.py
test/test_http.py
test/test_version.py
test/util/__init__.py
test/util/cli_helpers.py
conjur_client-0.1.1.dist-info/LICENSE.md
conjur_client-0.1.1.dist-info/METADATA
conjur_client-0.1.1.dist-info/WHEEL
conjur_client-0.1.1.dist-info/entry_points.txt
conjur_client-0.1.1.dist-info/top_level.txt
conjur_client-0.1.1.dist-info/zip-safe
conjur_client-0.1.1.dist-info/RECORD
